cap_decompiler-0.1.3.dist-info/metadata.json
cap_decompiler-0.1.3.dist-info/WHEEL
cap_decompiler-0.1.3.dist-info/DESCRIPTION.rst
cap_decompiler-0.1.3.dist-info/METADATA
cap_decompiler-0.1.3.dist-info/RECORD
cap_decompiler-0.1.3.dist-info/top_level.txt
cap_decompiler/pruner.py
cap_decompiler/decompiler.py
cap_decompiler/expressions.py
cap_decompiler/iterators.py
cap_decompiler/renamer.py
cap_decompiler/decompiler_gui.py
cap_decompiler/propagator.py
cap_decompiler/objdump-decompiler.py
cap_decompiler/ssa.py
cap_decompiler/graph.py
cap_decompiler/callconv.py
cap_decompiler/__init__.py
cap_decompiler/statements.py
cap_decompiler/host/dis.py
cap_decompiler/host/ui.py
cap_decompiler/host/__init__.py
cap_decompiler/host/capstone/__init__.py
cap_decompiler/host/capstone/dis/intel.py
cap_decompiler/host/capstone/dis/__init__.py
cap_decompiler/host/ida/__init__.py
cap_decompiler/host/ida/dis/intel.py
cap_decompiler/host/ida/dis/__init__.py
cap_decompiler/host/ida/ui/browser.py
cap_decompiler/host/ida/ui/graph_test.py
cap_decompiler/host/ida/ui/__init__.py
cap_decompiler/host/ida/ui/main.py
cap_decompiler/host/ida/ui/decompiler_form.py
cap_decompiler/tests/run.py
cap_decompiler/tests/data/fib-x86-objdump
cap_decompiler/tests/data/loops-x86-objdump
cap_decompiler/tests/data/Makefile
cap_decompiler/tests/data/conditionals-x64-objdump
cap_decompiler/tests/data/conditionals.c
cap_decompiler/tests/data/fib.c
cap_decompiler/tests/data/increments.c
cap_decompiler/tests/data/calls.c
cap_decompiler/tests/data/conditionals-x86-objdump
cap_decompiler/tests/data/loops.c
cap_decompiler/tests/common/disassembler.py
cap_decompiler/tests/common/__init__.py
cap_decompiler/tests/common/ply/ir_parser.py
cap_decompiler/tests/common/ply/ir_lexer.py
cap_decompiler/tests/common/ply/__init__.py
cap_decompiler/tests/unit/test_graph.py
cap_decompiler/tests/unit/test_ssa.py
cap_decompiler/tests/unit/test_helper.py
cap_decompiler/tests/unit/test_args.py
cap_decompiler/tests/unit/test_prune.py
cap_decompiler/tests/unit/test_conditionals.py
cap_decompiler/tests/unit/test_fib.py
cap_decompiler/tests/unit/test_stack.py
cap_decompiler/tests/unit/__init__.py
cap_decompiler/tests/unit/test_ir.py
